transrot/__init__.py
transrot/_version.py
transrot/transrot.py
transrot-0.0.1.dist-info/LICENSE
transrot-0.0.1.dist-info/METADATA
transrot-0.0.1.dist-info/WHEEL
transrot-0.0.1.dist-info/top_level.txt
transrot-0.0.1.dist-info/RECORD
