Metadata-Version: 2.1
Name: transrot
Version: 0.0.1
Summary: Lightweight Python package to calculate translational vector and rotational matrix between two sets of 3D coordinates
Author-email: Alejandro Martínez-León <ale94mleon@gmail.com>
Project-URL: Hompage, https://github.com/ale94mleon/transrot
Project-URL: Issues, https://github.com/ale94mleon/tutorial/transrot
Keywords: science,chemistry,biology,drug-design
Classifier: Development Status :: 2 - Pre-Alpha
Classifier: Operating System :: OS Independent
Classifier: Intended Audience :: Science/Research
Classifier: License :: OSI Approved :: MIT License
Classifier: Programming Language :: Python :: 3
Classifier: Topic :: Scientific/Engineering :: Mathematics
Classifier: Topic :: Scientific/Engineering :: Bio-Informatics
Classifier: Topic :: Scientific/Engineering :: Chemistry
Requires-Python: >=3
License-File: LICENSE
Requires-Dist: numpy
Provides-Extra: dev
Requires-Dist: pytest ; extra == 'dev'
